{"skeleton":{"hash":"AgmSg/UcSYmh0G+u+ofI0c/NaI8","spine":"3.8.75","x":-53.92,"y":-70.55,"width":103,"height":139,"images":"./materials/","audio":""},"bones":[{"name":"root"},{"name":"zhiliao","parent":"root","x":0.1},{"name":"glow_right_00002_00002","parent":"zhiliao","x":0.18,"y":-0.07},{"name":"glow_right_00002_2","parent":"zhiliao","x":1.07,"y":0.09},{"name":"zhiliao2","parent":"zhiliao","x":-0.01,"y":-1.27},{"name":"+_00004","parent":"zhiliao","x":0.28,"y":0.2},{"name":"+_4","parent":"zhiliao","x":0.28,"y":0.2},{"name":"+_5","parent":"zhiliao","x":0.28,"y":0.2},{"name":"+_6","parent":"zhiliao","x":-0.11,"y":0.78},{"name":"+_7","parent":"zhiliao","x":-0.11,"y":0.78},{"name":"+_8","parent":"zhiliao","x":-0.11,"y":0.78},{"name":"+_9","parent":"zhiliao","rotation":-0.04,"x":-0.11,"y":0.78},{"name":"+_10","parent":"zhiliao","x":-0.11,"y":0.78},{"name":"+_11","parent":"zhiliao","x":-0.11,"y":0.78}],"slots":[{"name":"glow_an_00002","bone":"glow_right_00002_00002","attachment":"glow_an_00002"},{"name":"glow_right_00002_00002","bone":"glow_right_00002_2","attachment":"glow_right_00002_00002"},{"name":"aixin_00004","bone":"zhiliao2","color":"fcff87ff"},{"name":"+_00004","bone":"+_00004","attachment":"+_00004"},{"name":"+_4","bone":"+_4","attachment":"+_00004"},{"name":"+_5","bone":"+_5","attachment":"+_00004"},{"name":"+_6","bone":"+_6","attachment":"+_00004"},{"name":"+_10","bone":"+_10","attachment":"+_00004"},{"name":"+_11","bone":"+_11","attachment":"+_00004"},{"name":"+_7","bone":"+_7","attachment":"+_00004"},{"name":"+_9","bone":"+_9","attachment":"+_00004"},{"name":"+_8","bone":"+_8","attachment":"+_00004"}],"skins":[{"name":"default","attachments":{"glow_right_00002_00002":{"glow_right_00002_00002":{"x":-0.41,"y":-0.22,"width":60,"height":104}},"glow_an_00002":{"glow_an_00002":{"x":-2.7,"y":-0.98,"width":103,"height":139}},"+_00004":{"+_00004":{"x":-0.13,"y":0.01,"scaleX":0.5,"scaleY":0.5,"width":42,"height":44}},"+_5":{"+_00004":{"x":-0.13,"y":0.01,"scaleX":0.5,"scaleY":0.5,"width":42,"height":44}},"+_6":{"+_00004":{"x":-0.13,"y":0.01,"scaleX":0.5,"scaleY":0.5,"width":42,"height":44}},"+_7":{"+_00004":{"x":-0.13,"y":0.01,"scaleX":0.5,"scaleY":0.5,"width":42,"height":44}},"+_8":{"+_00004":{"x":-0.13,"y":0.01,"scaleX":0.5,"scaleY":0.5,"width":42,"height":44}},"+_9":{"+_00004":{"x":-0.13,"y":0.01,"scaleX":0.5,"scaleY":0.5,"width":42,"height":44}},"+_4":{"+_00004":{"x":-0.13,"y":0.01,"scaleX":0.5,"scaleY":0.5,"width":42,"height":44}},"aixin_00004":{"aixin111_00005_00005":{"y":0.5,"width":46,"height":43},"aixin111_00005_00006":{"y":0.5,"width":46,"height":43},"aixin111_00005_00007":{"y":0.5,"width":46,"height":43},"aixin111_00005_00008":{"y":0.5,"width":46,"height":43},"aixin111_00012":{"y":0.5,"width":46,"height":43},"aixin_0001_00006":{"y":0.5,"width":46,"height":43},"aixin_00004":{"x":0.07,"y":-1.02,"width":46,"height":43}},"+_10":{"+_00004":{"x":-0.13,"y":0.01,"scaleX":0.5,"scaleY":0.5,"width":42,"height":44}},"+_11":{"+_00004":{"x":-0.13,"y":0.01,"scaleX":0.5,"scaleY":0.5,"width":42,"height":44}}}}],"animations":{"zhiliao":{"slots":{"+_10":{"color":[{"time":0.1667,"color":"ffffff00"},{"time":0.3,"color":"ffffffbe"},{"time":0.8667,"color":"ffffff00"}],"attachment":[{"name":null},{"time":0.1667,"name":"+_00004"}]},"+_11":{"color":[{"time":0.3,"color":"ffffff00"},{"time":0.4333,"color":"ffffffbe"},{"time":0.8667,"color":"ffffff00"}],"attachment":[{"name":null},{"time":0.3,"name":"+_00004"}]},"+_7":{"color":[{"time":0.1,"color":"ffffffd1"},{"time":0.4,"color":"ffffff00"}],"attachment":[{"name":null},{"time":0.1,"name":"+_00004"}]},"+_5":{"color":[{"time":0.1,"color":"ffffffd1","curve":"stepped"},{"time":0.5,"color":"ffffffd1"},{"time":0.5667,"color":"ffffff00"}],"attachment":[{"name":null},{"time":0.1,"name":"+_00004"}]},"+_9":{"color":[{"time":0.3333,"color":"ffffff00"},{"time":0.4,"color":"ffffffc7"},{"time":0.9,"color":"ffffff00"}],"attachment":[{"name":null},{"time":0.3333,"name":"+_00004"}]},"glow_right_00002_00002":{"color":[{"color":"ffffff00","curve":0.25,"c3":0.75},{"time":0.0667,"color":"ffffffff","curve":0.25,"c3":0.75},{"time":0.4,"color":"ffffff00"}]},"aixin_00004":{"color":[{"time":0.0333,"color":"ffffff00"},{"time":0.0667,"color":"ffffffff","curve":"stepped"},{"time":0.1333,"color":"ffffffff"},{"time":0.8,"color":"ffffff00"}],"attachment":[{"time":0.0333,"name":"aixin_00004"},{"time":0.0667,"name":"aixin_0001_00006"},{"time":0.1,"name":"aixin111_00005_00005"},{"time":0.1667,"name":"aixin111_00005_00006"},{"time":0.2,"name":"aixin111_00005_00007"},{"time":0.3,"name":"aixin111_00005_00008"}]},"+_4":{"color":[{"time":0.1,"color":"ffffffe6","curve":"stepped"},{"time":0.5,"color":"ffffffe6"},{"time":0.6333,"color":"ffffff00"}],"attachment":[{"name":null},{"time":0.1,"name":"+_00004"}]},"+_6":{"color":[{"time":0.1,"color":"ffffffff"},{"time":0.3,"color":"ffffff00"}],"attachment":[{"name":null},{"time":0.1,"name":"+_00004"}]},"glow_an_00002":{"color":[{"color":"ffffff00","curve":0.25,"c3":0.75},{"time":0.0667,"color":"ffffffff","curve":0.25,"c3":0.75},{"time":1,"color":"ffffff00"}]},"+_00004":{"color":[{"time":0.3333,"color":"ffffffff"},{"time":0.7667,"color":"ffffff00"}],"attachment":[{"name":null},{"time":0.1,"name":"+_00004"}]},"+_8":{"color":[{"time":0.1,"color":"ffffffe6"},{"time":0.2667,"color":"ffffffb4"},{"time":0.5,"color":"ffffff00"}],"attachment":[{"name":null},{"time":0.1,"name":"+_00004"}]}},"bones":{"glow_right_00002_00002":{"rotate":[{"time":0.1333,"angle":-0.02}],"scale":[{"x":0,"y":0,"curve":0.25,"c3":0.75},{"time":0.0667,"curve":0.25,"c3":0.75},{"time":1,"x":1.2,"y":1.2}]},"glow_right_00002_2":{"scale":[{"time":0.0667,"curve":0.25,"c3":0.75},{"time":0.4,"x":0.6}]},"zhiliao2":{"scale":[{"time":0.0333,"x":0.4,"y":0.4,"curve":0,"c2":0.98,"c3":0.343,"c4":0.99},{"time":0.8,"x":2,"y":2}]},"+_00004":{"translate":[{"time":0.1},{"time":0.7667,"y":27.77}],"scale":[{"time":0.1},{"time":0.7667,"x":0.2,"y":0.2}]},"+_4":{"translate":[{"time":0.1,"x":21.87,"y":-14.77},{"time":0.6333,"x":21.87,"y":-4.33}],"scale":[{"time":0.1,"x":0.35,"y":0.35},{"time":0.6333,"x":0.2,"y":0.2}]},"+_5":{"translate":[{"time":0.1,"x":-11.23,"y":12.02},{"time":0.5667,"x":-11.23,"y":32.97}],"scale":[{"time":0.1,"x":0.35,"y":0.35},{"time":0.5667,"x":0,"y":0}]},"+_6":{"translate":[{"time":0.1,"x":17.44,"y":8.12},{"time":0.8667,"x":17.44,"y":35.35}],"scale":[{"time":0.1,"x":0.6,"y":0.6},{"time":0.8667,"x":0.1,"y":0.1}]},"+_7":{"translate":[{"time":0.1,"x":-7.97,"y":-24.06},{"time":0.8,"x":-7.97,"y":6.47}],"scale":[{"time":0.1,"x":0.75,"y":0.75},{"time":0.8,"x":0.2,"y":0.2}]},"+_8":{"translate":[{"time":0.1,"x":25.46,"y":0.53},{"time":0.5,"x":24.86,"y":15.71}],"scale":[{"time":0.1,"x":0.3,"y":0.3},{"time":0.5,"x":0.1,"y":0.1}]},"+_9":{"translate":[{"time":0.3333,"x":-18.86,"y":1.81},{"time":0.9,"x":-18.85,"y":15.3}],"scale":[{"time":0.3333,"x":0.62,"y":0.62},{"time":0.9,"x":0.3,"y":0.3}]},"+_10":{"translate":[{"time":0.1667,"x":11.94,"y":-7.65},{"time":0.8667,"x":11.94,"y":7.97}],"scale":[{"time":0.1667,"x":0.5,"y":0.5},{"time":0.8667,"x":0.2,"y":0.2}]},"+_11":{"translate":[{"time":0.3,"x":2.93,"y":-17.64},{"time":0.8667,"x":2.93,"y":-7.15}],"scale":[{"time":0.3,"x":0.3,"y":0.3},{"time":0.8667,"x":0.1,"y":0.1}]}}}}}